isaac/__init__.py
isaac/__main__.py
isaac/cli.py
isaac/command.py
isaac/constants.py
isaac/globals.py
isaac/meta.py
isaac/settings.py
isaac/sync.py
isaac/theme.py
isaac/types.py
isaac/utils.py
isaac/listeners/__init__.py
isaac/listeners/py_listener.py
isaac/speakers/__init__.py
isaac/speakers/piper.py
isaac/speakers/pocket.py
isaac/speakers/utils.py
isaac/thinkers/__init__.py
isaac/thinkers/gemini.py
isaac/thinkers/groq.py
isaac/thinkers/utils.py
py_isaac-0.3.4.dist-info/licenses/LICENSE
py_isaac-0.3.4.dist-info/METADATA
py_isaac-0.3.4.dist-info/WHEEL
py_isaac-0.3.4.dist-info/entry_points.txt
py_isaac-0.3.4.dist-info/top_level.txt
py_isaac-0.3.4.dist-info/RECORD
