Metadata-Version: 2.4
Name: py-isaac
Version: 0.3.4
Summary: Cooles locally run AI assistant
Home-page: https://github.com/n1teshy/py-isaac
Author: Nitesh Yadav
Author-email: nitesh.txt@gmail.com
License: GPL-3.0-or-later
Keywords: AI assistant,local assistant
Platform: Posix; Windows
Classifier: Intended Audience :: Developers
Classifier: Programming Language :: Python :: 3
Classifier: Operating System :: OS Independent
Requires-Python: >=3.9
License-File: LICENSE
Requires-Dist: sounddevice
Requires-Dist: py-listener
Requires-Dist: yapper-tts
Requires-Dist: psutil
Requires-Dist: numpy
Requires-Dist: rich
Requires-Dist: requests
Requires-Dist: pyreadline3; sys_platform == "win32"
Provides-Extra: custom-voice
Requires-Dist: pocket-tts; extra == "custom-voice"
Dynamic: author
Dynamic: author-email
Dynamic: classifier
Dynamic: description
Dynamic: description-content-type
Dynamic: home-page
Dynamic: keywords
Dynamic: license
Dynamic: license-file
Dynamic: platform
Dynamic: provides-extra
Dynamic: requires-dist
Dynamic: requires-python
Dynamic: summary
